gym_gomoku/__init__.py
gym_gomoku/envs/__init__.py
gym_gomoku/envs/gomoku.py
gym_gomoku/envs/util.py
gym_gomoku-0.0.1.dist-info/DESCRIPTION.rst
gym_gomoku-0.0.1.dist-info/METADATA
gym_gomoku-0.0.1.dist-info/RECORD
gym_gomoku-0.0.1.dist-info/WHEEL
gym_gomoku-0.0.1.dist-info/metadata.json
gym_gomoku-0.0.1.dist-info/top_level.txt
