Metadata-Version: 2.0
Name: gym-gomoku
Version: 0.0.1
Summary: Game Gomoku or Five-In-a-Row Gym Environment
Home-page: UNKNOWN
Author: Xichen Ding
Author-email: dingo0927@126.com
License: MIT
Keywords: gym gomoku reinforcement learning
Platform: UNKNOWN
Classifier: Development Status :: 4 - Beta
Classifier: Programming Language :: Python :: 2.7
Classifier: Programming Language :: Python :: 3
Classifier: Topic :: Scientific/Engineering
Classifier: Topic :: Software Development
Classifier: Topic :: Scientific/Engineering :: Artificial Intelligence
Requires-Dist: gym
